setup.py
fallbackserve/__init__.py
fallbackserve/storage.py
fallbackserve/views.py
glamkit_fallbackserve.egg-info/PKG-INFO
glamkit_fallbackserve.egg-info/SOURCES.txt
glamkit_fallbackserve.egg-info/dependency_links.txt
glamkit_fallbackserve.egg-info/not-zip-safe
glamkit_fallbackserve.egg-info/top_level.txt