Metadata-Version: 1.0
Name: glamkit-fallbackserve
Version: 0.1
Summary: Makes your life easier when dealing with media during the development of Django apps
Home-page: http://github.com/glamkit/glamkit-fallbackserve
Author: Wil Tan
Author-email: wil@interaction.net.au
License: UNKNOWN
Platform: UNKNOWN
Classifier: Development Status :: 4 - Beta
Classifier: Environment :: Web Environment
Classifier: Intended Audience :: Developers
Classifier: License :: OSI Approved :: BSD License
Classifier: Operating System :: OS Independent
Classifier: Programming Language :: Python
Classifier: Framework :: Django
